QGDT/__init__.py
QGDT/correlation_calculate.py
QGDT/frequency_calculate.py
QGDT/qgdt.py
QGDT/question_generate.py
QGDT/similarity_calculate.py
QGDT/templates_init.py
QGDT/tools.py
QGDT/train_models.py
QGDT/data/__init__.py
QGDT/data/rnn.csv
QGDT/data/rnn_train.csv
QGDT/data/svm.csv
QGDT/data/svm_train.csv
QGDT/data/w2v.csv
QGDT/data/w2v_train.csv
QGDT/models/__init__.py
QGDT/models/rnn
QGDT/models/rnn_dict
QGDT/models/svm
QGDT/models/w2v
QGDT/templates_x/__init__.py
QGDT/templates_x/templates_x1.py
QGDT/templates_x/templates_x2.py
QGDT/templates_x/templates_x3.py
QGDT_cpu-0.3.3.dist-info/DESCRIPTION.rst
QGDT_cpu-0.3.3.dist-info/METADATA
QGDT_cpu-0.3.3.dist-info/RECORD
QGDT_cpu-0.3.3.dist-info/WHEEL
QGDT_cpu-0.3.3.dist-info/metadata.json
QGDT_cpu-0.3.3.dist-info/top_level.txt
